compute_api_client/__init__.py
compute_api_client/api_client.py
compute_api_client/api_response.py
compute_api_client/configuration.py
compute_api_client/exceptions.py
compute_api_client/rest.py
compute_api_client/api/__init__.py
compute_api_client/api/algorithms_api.py
compute_api_client/api/auth_config_api.py
compute_api_client/api/backend_api.py
compute_api_client/api/backend_types_api.py
compute_api_client/api/batch_jobs_api.py
compute_api_client/api/commits_api.py
compute_api_client/api/files_api.py
compute_api_client/api/final_results_api.py
compute_api_client/api/health_api.py
compute_api_client/api/jobs_api.py
compute_api_client/api/languages_api.py
compute_api_client/api/members_api.py
compute_api_client/api/metadata_api.py
compute_api_client/api/permissions_api.py
compute_api_client/api/projects_api.py
compute_api_client/api/reservations_api.py
compute_api_client/api/results_api.py
compute_api_client/api/teams_api.py
compute_api_client/api/transactions_api.py
compute_api_client/api/users_api.py
compute_api_client/docs/Algorithm.md
compute_api_client/docs/AlgorithmIn.md
compute_api_client/docs/AlgorithmType.md
compute_api_client/docs/AlgorithmsApi.md
compute_api_client/docs/AuthConfig.md
compute_api_client/docs/AuthConfigApi.md
compute_api_client/docs/Backend.md
compute_api_client/docs/BackendApi.md
compute_api_client/docs/BackendIn.md
compute_api_client/docs/BackendMessage.md
compute_api_client/docs/BackendPatch.md
compute_api_client/docs/BackendStatus.md
compute_api_client/docs/BackendType.md
compute_api_client/docs/BackendTypePatch.md
compute_api_client/docs/BackendTypesApi.md
compute_api_client/docs/BackendWithAuthentication.md
compute_api_client/docs/BatchJob.md
compute_api_client/docs/BatchJobIn.md
compute_api_client/docs/BatchJobStatus.md
compute_api_client/docs/BatchJobsApi.md
compute_api_client/docs/Commit.md
compute_api_client/docs/CommitIn.md
compute_api_client/docs/CommitsApi.md
compute_api_client/docs/CompilePayload.md
qi_compute_api_client-0.56.0.dist-info/METADATA
qi_compute_api_client-0.56.0.dist-info/WHEEL
qi_compute_api_client-0.56.0.dist-info/licenses/LICENSE.md
qi_compute_api_client-0.56.0.dist-info/RECORD
