Metadata-Version: 2.4
Name: qi-compute-api-client
Version: 0.56.0
Summary: An API client for the Compute Job Manager of Quantum Inspire.
Project-URL: Repository, https://github.com/QuTech-Delft/compute-api-client
Author-email: Quantum Inspire <support@quantum-inspire.eu>
License-Expression: Apache-2.0
License-File: LICENSE.md
Classifier: Development Status :: 3 - Alpha
Classifier: License :: OSI Approved :: Apache Software License
Classifier: Programming Language :: Python :: 3
Classifier: Programming Language :: Python :: 3.10
Classifier: Programming Language :: Python :: 3.11
Classifier: Programming Language :: Python :: 3.12
Classifier: Programming Language :: Python :: 3.13
Requires-Python: <3.14,>=3.10
Requires-Dist: aiohttp-retry==2.9.1
Requires-Dist: aiohttp==3.13.3
Requires-Dist: pydantic==2.12.5
Requires-Dist: python-dateutil==2.9.0.post0
Requires-Dist: requests==2.32.5
Requires-Dist: typing-extensions==4.15.0
Requires-Dist: urllib3==2.6.3
